odoo9_addon_stock_inventory_discrepancy-9.0.1.0.0-py2.7-nspkg.pth
odoo9_addon_stock_inventory_discrepancy-9.0.1.0.0.dist-info/top_level.txt
odoo9_addon_stock_inventory_discrepancy-9.0.1.0.0.dist-info/WHEEL
odoo9_addon_stock_inventory_discrepancy-9.0.1.0.0.dist-info/RECORD
odoo9_addon_stock_inventory_discrepancy-9.0.1.0.0.dist-info/metadata.json
odoo9_addon_stock_inventory_discrepancy-9.0.1.0.0.dist-info/DESCRIPTION.rst
odoo9_addon_stock_inventory_discrepancy-9.0.1.0.0.dist-info/METADATA
odoo9_addon_stock_inventory_discrepancy-9.0.1.0.0.dist-info/namespace_packages.txt
odoo_addons/stock_inventory_discrepancy/__openerp__.py
odoo_addons/stock_inventory_discrepancy/__init__.py
odoo_addons/stock_inventory_discrepancy/README.rst
odoo_addons/stock_inventory_discrepancy/security/stock_inventory_discrepancy_security.xml
odoo_addons/stock_inventory_discrepancy/models/stock_inventory.py
odoo_addons/stock_inventory_discrepancy/models/stock_inventory_line.py
odoo_addons/stock_inventory_discrepancy/models/stock_location.py
odoo_addons/stock_inventory_discrepancy/models/stock_warehouse.py
odoo_addons/stock_inventory_discrepancy/models/__init__.py
odoo_addons/stock_inventory_discrepancy/views/stock_inventory_view.xml
odoo_addons/stock_inventory_discrepancy/views/stock_location_view.xml
odoo_addons/stock_inventory_discrepancy/views/stock_warehouse_view.xml
odoo_addons/stock_inventory_discrepancy/tests/test_inventory_discrepancy.py
odoo_addons/stock_inventory_discrepancy/tests/__init__.py
