Metadata-Version: 2.0
Name: odoo9-addon-stock-inventory-discrepancy
Version: 9.0.1.0.0
Summary: Adds the capability to show the discrepancy of every line in an inventory and to block the inventory validation when the discrepancy is over a user defined threshold.
Home-page: https://github.com/OCA/stock-logistics-warehouse
Author: Eficent, Odoo Community Association (OCA)
Author-email: support@odoo-community.org
License: AGPL-3
Platform: UNKNOWN
Requires-Dist: odoo (<9.1a,>=9.0a)
Classifier: Programming Language :: Python :: 2.7
Classifier: Framework :: Odoo
Classifier: License :: OSI Approved :: GNU Affero General Public License v3
